[
  {
    "Fleet Member Name": "[SSR] Kiwi",
    "All Time Rank": "7",
    "BigBook Link": "https://bigbook.app/captain/6209343"
  },
  {
    "Fleet Member Name": "[SSR] (AG2) MrScott",
    "All Time Rank": "9",
    "BigBook Link": "https://bigbook.app/captain/4021654"
  },
  {
    "Fleet Member Name": "[SSR] GTMET",
    "All Time Rank": "17",
    "BigBook Link": "https://bigbook.app/captain/3897545"
  },
  {
    "Fleet Member Name": "[SSR] This Sisko1",
    "All Time Rank": "22",
    "BigBook Link": "https://bigbook.app/captain/236734"
  },
  {
    "Fleet Member Name": "[SSR] Barkley",
    "All Time Rank": "32",
    "BigBook Link": "https://bigbook.app/captain/407995"
  },
  {
    "Fleet Member Name": "[SSR] Big Bird",
    "All Time Rank": "41",
    "BigBook Link": "https://bigbook.app/captain/5910149"
  },
  {
    "Fleet Member Name": "[SSR] Callimachus",
    "All Time Rank": "43",
    "BigBook Link": "https://bigbook.app/captain/4503983"
  },
  {
    "Fleet Member Name": "[SSR] Gazoo",
    "All Time Rank": "46",
    "BigBook Link": "https://bigbook.app/captain/4718368"
  },
  {
    "Fleet Member Name": "[SSR] Evans of Wales",
    "All Time Rank": "66",
    "BigBook Link": "https://bigbook.app/captain/6874904"
  },
  {
    "Fleet Member Name": "¦SSR¦ Artaniel",
    "All Time Rank": "75",
    "BigBook Link": "https://bigbook.app/captain/273018"
  },
  {
    "Fleet Member Name": "[SSR] AJ Warp 9",
    "All Time Rank": "80",
    "BigBook Link": "https://bigbook.app/captain/1036360"
  },
  {
    "Fleet Member Name": "[SSR] Krakho",
    "All Time Rank": "82",
    "BigBook Link": "https://bigbook.app/captain/7674422"
  },
  {
    "Fleet Member Name": "[SSR] gmLorca (AG1)",
    "All Time Rank": "83",
    "BigBook Link": "https://bigbook.app/captain/5791194"
  },
  {
    "Fleet Member Name": "[SSR] TinkerTailor",
    "All Time Rank": "98",
    "BigBook Link": "https://bigbook.app/captain/976090"
  },
  {
    "Fleet Member Name": "[SSR] Nolian",
    "All Time Rank": "101",
    "BigBook Link": "https://bigbook.app/captain/7550015"
  }
]
